flask_textile.py
Flask_Textile-0.4.1.post1.dist-info/LICENSE
Flask_Textile-0.4.1.post1.dist-info/METADATA
Flask_Textile-0.4.1.post1.dist-info/WHEEL
Flask_Textile-0.4.1.post1.dist-info/top_level.txt
Flask_Textile-0.4.1.post1.dist-info/RECORD
