Metadata-Version: 2.1
Name: Flask-Textile
Version: 0.4.1.post1
Summary: Textile parsing from within Flask
Home-page: https://git.sr.ht/~ethet/flask-textile
Author: ethet
Author-email: eth@ethet.org
License: BSD
Platform: any
Classifier: Environment :: Web Environment
Classifier: Intended Audience :: Developers
Classifier: License :: OSI Approved :: BSD License
Classifier: Operating System :: OS Independent
Classifier: Programming Language :: Python
Classifier: Framework :: Flask
Classifier: Topic :: Internet :: WWW/HTTP :: Dynamic Content
Classifier: Topic :: Software Development :: Libraries :: Python Modules
Requires-Dist: Flask
Requires-Dist: textile
